{
	"partitions" : [
		{
			"name" : "Top",
			"pins" : [
				{
					"name" : "ckey[0]",
					"strict" : false
				},
				{
					"name" : "ckey[1]",
					"strict" : false
				},
				{
					"name" : "ckey[2]",
					"strict" : false
				},
				{
					"name" : "ckey[3]",
					"strict" : false
				},
				{
					"name" : "ckey[4]",
					"strict" : false
				},
				{
					"name" : "ckey[5]",
					"strict" : false
				},
				{
					"name" : "ckey[6]",
					"strict" : false
				},
				{
					"name" : "ckey[7]",
					"strict" : false
				},
				{
					"name" : "done[0]",
					"strict" : false
				},
				{
					"name" : "CLOCK_50",
					"strict" : false
				},
				{
					"name" : "keyLength[7]",
					"strict" : false
				},
				{
					"name" : "keyLength[6]",
					"strict" : false
				},
				{
					"name" : "keyLength[5]",
					"strict" : false
				},
				{
					"name" : "keyLength[4]",
					"strict" : false
				},
				{
					"name" : "keyLength[3]",
					"strict" : false
				},
				{
					"name" : "keyLength[2]",
					"strict" : false
				},
				{
					"name" : "keyLength[1]",
					"strict" : false
				},
				{
					"name" : "keyLength[0]",
					"strict" : false
				},
				{
					"name" : "rst_n",
					"strict" : false
				},
				{
					"name" : "start",
					"strict" : false
				},
				{
					"name" : "key[8]",
					"strict" : false
				},
				{
					"name" : "key[16]",
					"strict" : false
				},
				{
					"name" : "key[0]",
					"strict" : false
				},
				{
					"name" : "key[24]",
					"strict" : false
				},
				{
					"name" : "key[17]",
					"strict" : false
				},
				{
					"name" : "key[9]",
					"strict" : false
				},
				{
					"name" : "key[1]",
					"strict" : false
				},
				{
					"name" : "key[25]",
					"strict" : false
				},
				{
					"name" : "key[10]",
					"strict" : false
				},
				{
					"name" : "key[18]",
					"strict" : false
				},
				{
					"name" : "key[2]",
					"strict" : false
				},
				{
					"name" : "key[26]",
					"strict" : false
				},
				{
					"name" : "key[19]",
					"strict" : false
				},
				{
					"name" : "key[11]",
					"strict" : false
				},
				{
					"name" : "key[3]",
					"strict" : false
				},
				{
					"name" : "key[27]",
					"strict" : false
				},
				{
					"name" : "key[12]",
					"strict" : false
				},
				{
					"name" : "key[20]",
					"strict" : false
				},
				{
					"name" : "key[4]",
					"strict" : false
				},
				{
					"name" : "key[28]",
					"strict" : false
				},
				{
					"name" : "key[21]",
					"strict" : false
				},
				{
					"name" : "key[5]",
					"strict" : false
				},
				{
					"name" : "key[29]",
					"strict" : false
				},
				{
					"name" : "key[13]",
					"strict" : false
				},
				{
					"name" : "key[14]",
					"strict" : false
				},
				{
					"name" : "key[22]",
					"strict" : false
				},
				{
					"name" : "key[6]",
					"strict" : false
				},
				{
					"name" : "key[30]",
					"strict" : false
				},
				{
					"name" : "key[23]",
					"strict" : false
				},
				{
					"name" : "key[15]",
					"strict" : false
				},
				{
					"name" : "key[7]",
					"strict" : false
				},
				{
					"name" : "key[31]",
					"strict" : false
				}
			]
		}
	]
}